adder/0_design/adder.v
/* only combinational ckt
 * Not syncronous 
 */
module adder (
input wire a,
input wire b,
input wire c_in,
output  sum,
output  c_out
);
assign sum = a^b^c_in ;
assign c_out = (a|b)&c_in | (a&b) ;
endmodule

adder/1_tb/adder_tb.v
`timescale 1ns/1ps
module adder_tb ;
/* inputs */
wire sum ;
wire c_out ;

/* outputs */
reg a ;
reg b ;
reg c_in ;

adder DUT (.a(a), .b(b), .c_in(c_in), .sum(sum), .c_out(c_out)) ;

integer i ;
initial begin
  $display("Simulation started");
  $dumpfile("./2_sim/adder.vcd");
  $dumpvars(0, adder_tb);
  a = 0;
  b = 0;
  c_in = 0;
  for (i = 0; i < 7; i = i + 1 ) begin //{
    #1 ;
    c_in = ~c_in ;
    if ( ~c_in) begin //{
      b = ~b ;
    end //}
    if ( b && c_in) begin //{
      a = ~a ;
    end//}
  end //}
  $display("Simulation finished");
  #100 $finish;
end
endmodule

adder/2_sim/adder.vcd
$date
	Wed Feb 14 06:42:01 2024
$end
$version
	Icarus Verilog
$end
$timescale
	1s
$end
$scope module adder_tb $end
$var wire 1 ! sum $end
$var wire 1 " c_out $end
$var reg 1 # a $end
$var reg 1 $ b $end
$var reg 1 % c_in $end
$var integer 32 & i [31:0] $end
$scope module DUT $end
$var wire 1 # a $end
$var wire 1 $ b $end
$var wire 1 % c_in $end
$var wire 1 " c_out $end
$var wire 1 ! sum $end
$upscope $end
$upscope $end
$enddefinitions $end
$comment Show the parameter values. $end
$dumpall
$end
#0
$dumpvars
b0 &
0%
0$
0#
0"
0!
$end
#1
1!
b1 &
1%
#2
1!
b10 &
1$
0%
#3
1"
1!
b11 &
1#
1%
#4
0"
1!
b100 &
0$
0%
#5
1"
0!
b101 &
1%
#6
0!
b110 &
1$
0%
#7
0!
b111 &
0#
1%
